taurus_publisher/__init__.py
taurus_publisher/publisher.py
taurus_publisher/helpers/redis/connection.py
taurus_publisher-1.0.2.dist-info/METADATA
taurus_publisher-1.0.2.dist-info/WHEEL
taurus_publisher-1.0.2.dist-info/entry_points.txt
taurus_publisher-1.0.2.dist-info/license_files/LICENCE
taurus_publisher-1.0.2.dist-info/RECORD
