Metadata-Version: 2.1
Name: taurus-publisher
Version: 1.0.2
Summary: Python library using LUA script to send for redis a job for Taurus queue
Project-URL: Homepage, https://github.com/not-empty/taurus-publisher-python
Project-URL: Issues, https://github.com/not-empty/taurus-publisher-python/issues
Author-email: Not Empty Foundation <dev@not-empty.org>
Classifier: License :: OSI Approved :: GNU General Public License v3 (GPLv3)
Classifier: Operating System :: OS Independent
Classifier: Programming Language :: Python :: 3
Requires-Python: >=3.6.9
Requires-Dist: redis>=4.3.6
Requires-Dist: ulid-py>=1.1.0
